{
  "ATH_SYNC_ALL": "100",
  "TLM_CMD_AI_SEND": "0",
  "TLM_CMD_IGNORE": "Work Stop Train Build Research SetGatherPoint Cancel Enter Eject Empower",
  "TLM_CLIENT_HB_FREQ": "300",
  "TLM_MATCH_HB_FREQ": "300",
  "TLM_MATCHPERF_HB_FREQ": "300",
  "TLM_SNAP_FREQ": "300",
  "TLM_ASSET_FREQ": "150",
  "TLM_UISESSION_PERCENT": "10",
  "RL_USE_WEBSOCKET_PERCENT": "100",
  "RL_KEEPALIVE": "20",
  "RL_DISCONNECT": "30",
  "RL_MISSPOLL": "3",
  "RL_TELEMSERVICE": "0",
  "RL_TELEMREPORTPCT": "1.0",
  "RL_MATCHTELEMPERIOD": "600",
  "RL_TELEMKINESISHOST": "kinesis.us-east-1.amazonaws.com",
  "RL_TELEMKINESISSTREAM": "s3DevStream",
  "RL_TELEMCELLHOST": "cardinal-int.maelstrom.gameservices.xboxlive.com",
  "RL_TELEMCELLPATH": "/tenants/cardinal/routes/game/",
  "RL_TELEMPLAYFABHOST": "C15F9.playfabapi.com",
  "RL_TELEMPLAYFABPATH": "/Event/WriteTelemetryEvents",
  "RL_CLUSTERNAME": "mythlive_",
  "RL_TITLEID": "46",
  "RL_OBSERVERCUSTOMDELAY": "180",
  "RL_OBSERVERMAX": "512",
  "RL_USE_AUTOMATCH2": "1",
  "RL_AUTOMATCH2_TEAM_FACTION_TYPE": "1",
  "RL_UPLOAD_TIMEOUT": "300000",
  "RL_CLOUDCACHETIME": "21600",
  "RL_CLOUD_CREDENTIAL_PROVIDER": "AZURE",
  "RL_ITEM_LOADOUTS_MAX": "50",
  "RL_CLAN_INVITE_EXPIRE_TIME_SEC": "43200",
  "RL_NUMBER_OF_GAMES_TO_RANK": "10",
  "RL_NUMBER_OF_EVENT_GAMES_TO_RANK": "5",
  "RL_WEB_ASSETS_ICONS_ROOT": "https://test-build-data.reliclink.com/",
  "RL_GLOBAL_REWARD_CURRENCY": "",
  "RL_SSO_URL": "https://sso.relic.com/en/steam?title=athens&"
}